{"activation": "relu", "alpha": 0.0001, "batch_size": "auto", "beta_1": 0.9, "beta_2": 0.999, "early_stopping": false, "epsilon": 1e-08, "hidden_layer_sizes": "[5]", "learning_rate": "constant", "learning_rate_init": 0.001, "max_fun": 15000, "max_iter": 2000, "momentum": 0.9, "n_iter_no_change": 10, "nesterovs_momentum": true, "power_t": 0.5, "random_state": null, "shuffle": true, "solver": "adam", "tol": 0.0001, "validation_fraction": 0.1, "verbose": false, "warm_start": false, "best_model_name": "MLP_TargetTransformed", "best_model_val_score": -3.51772968996758, "_timestamp": 1712168365.7229865, "_runtime": 3.331463575363159, "_step": 2, "mean_errors_train": 0.07410876855561722, "mean_errors_val": 0.05355839756634797, "mean_errors_test": 0.06618145871760713, "mean_errors_remaining": 0.09831215289905856, "mean_errors_grid": 0.1749143996470427, "true_validity_threshold": 0.03, "_wandb": {"runtime": 41}}